{"data_mtime":1751105873,"dep_lines":[42,42,44,34,42,43,13,14,15,16,17,18,19,31,32,1,1,1,1,1,1,1,1,1,1,1,1,1,1,1,1,1,51,52,54,51,53,50],"dep_prios":[10,10,5,5,20,5,10,10,10,5,5,5,5,10,10,5,20,20,30,30,30,30,30,30,30,30,30,30,30,30,30,30,10,10,5,20,5,10],"dependencies":["pandera.engines.numpy_engine","pandera.engines.pandas_engine","pandera.strategies.base_strategies","pandera.dtypes","pandera.engines","pandera.errors","operator","re","warnings","collections","copy","functools","typing","numpy","pandas","builtins","pandera.api.extensions","pandera.typing","_frozen_importlib","abc","pandas.core","pandas.core.arraylike","pandas.core.base","pandas.core.dtypes","pandas.core.dtypes.base","pandas.core.dtypes.dtypes","pandas.core.frame","pandas.core.generic","pandas.core.indexes","pandas.core.indexes.base","pandas.core.indexing","pandas.core.series"],"hash":"55e2115b7983985c98bb990a22e96e52cdcc563e","id":"pandera.strategies.pandas_strategies","ignore_all":true,"interface_hash":"8ccc2f3124bada4caac796136059c6ac9649c68c","mtime":1749432806,"options":{"allow_redefinition":false,"allow_untyped_globals":false,"always_false":[],"always_true":[],"bazel":false,"check_untyped_defs":false,"disable_bytearray_promotion":false,"disable_error_code":[],"disable_memoryview_promotion":false,"disabled_error_codes":[],"disallow_any_decorated":false,"disallow_any_explicit":false,"disallow_any_expr":false,"disallow_any_generics":false,"disallow_any_unimported":false,"disallow_incomplete_defs":false,"disallow_subclassing_any":false,"disallow_untyped_calls":false,"disallow_untyped_decorators":false,"disallow_untyped_defs":false,"enable_error_code":[],"enabled_error_codes":[],"extra_checks":false,"follow_imports":"normal","follow_imports_for_stubs":false,"follow_untyped_imports":false,"ignore_errors":false,"ignore_missing_imports":false,"implicit_optional":false,"implicit_reexport":true,"local_partial_types":false,"mypyc":false,"old_type_inference":false,"platform":"win32","plugins":[],"strict_bytes":false,"strict_concatenate":false,"strict_equality":false,"strict_optional":true,"warn_no_return":true,"warn_return_any":false,"warn_unreachable":false,"warn_unused_ignores":false},"path":"c:\\Users\\Ephel\\AppData\\Local\\Programs\\Python\\Python310\\lib\\site-packages\\pandera\\strategies\\pandas_strategies.py","plugin_data":null,"size":44628,"suppressed":["hypothesis.extra.numpy","hypothesis.extra.pandas","hypothesis.internal.filtering","hypothesis.extra","hypothesis.strategies","hypothesis"],"version_id":"1.15.0"}