{".class":"MypyFile","_fullname":"polars.io.database._inference","future_import_flags":["annotations"],"is_partial_stub_package":false,"is_stub":false,"names":{".class":"SymbolTable","Any":{".class":"SymbolTableNode","cross_ref":"typing.Any","kind":"Gdef"},"Binary":{".class":"SymbolTableNode","cross_ref":"polars.datatypes.classes.Binary","kind":"Gdef"},"Boolean":{".class":"SymbolTableNode","cross_ref":"polars.datatypes.classes.Boolean","kind":"Gdef"},"Date":{".class":"SymbolTableNode","cross_ref":"polars.datatypes.classes.Date","kind":"Gdef"},"Datetime":{".class":"SymbolTableNode","cross_ref":"polars.datatypes.classes.Datetime","kind":"Gdef"},"Decimal":{".class":"SymbolTableNode","cross_ref":"polars.datatypes.classes.Decimal","kind":"Gdef"},"Duration":{".class":"SymbolTableNode","cross_ref":"polars.datatypes.classes.Duration","kind":"Gdef"},"Float32":{".class":"SymbolTableNode","cross_ref":"polars.datatypes.classes.Float32","kind":"Gdef"},"Float64":{".class":"SymbolTableNode","cross_ref":"polars.datatypes.classes.Float64","kind":"Gdef"},"INTEGER_DTYPES":{".class":"SymbolTableNode","cross_ref":"polars.datatypes.group.INTEGER_DTYPES","kind":"Gdef"},"Int128":{".class":"SymbolTableNode","cross_ref":"polars.datatypes.classes.Int128","kind":"Gdef"},"Int16":{".class":"SymbolTableNode","cross_ref":"polars.datatypes.classes.Int16","kind":"Gdef"},"Int32":{".class":"SymbolTableNode","cross_ref":"polars.datatypes.classes.Int32","kind":"Gdef"},"Int64":{".class":"SymbolTableNode","cross_ref":"polars.datatypes.classes.Int64","kind":"Gdef"},"Int8":{".class":"SymbolTableNode","cross_ref":"polars.datatypes.classes.Int8","kind":"Gdef"},"List":{".class":"SymbolTableNode","cross_ref":"polars.datatypes.classes.List","kind":"Gdef"},"Null":{".class":"SymbolTableNode","cross_ref":"polars.datatypes.classes.Null","kind":"Gdef"},"PolarsDataType":{".class":"SymbolTableNode","cross_ref":"polars._typing.PolarsDataType","kind":"Gdef"},"String":{".class":"SymbolTableNode","cross_ref":"polars.datatypes.classes.String","kind":"Gdef"},"TYPE_CHECKING":{".class":"SymbolTableNode","cross_ref":"typing.TYPE_CHECKING","kind":"Gdef"},"Time":{".class":"SymbolTableNode","cross_ref":"polars.datatypes.classes.Time","kind":"Gdef"},"UInt16":{".class":"SymbolTableNode","cross_ref":"polars.datatypes.classes.UInt16","kind":"Gdef"},"UInt32":{".class":"SymbolTableNode","cross_ref":"polars.datatypes.classes.UInt32","kind":"Gdef"},"UInt64":{".class":"SymbolTableNode","cross_ref":"polars.datatypes.classes.UInt64","kind":"Gdef"},"UInt8":{".class":"SymbolTableNode","cross_ref":"polars.datatypes.classes.UInt8","kind":"Gdef"},"UNSIGNED_INTEGER_DTYPES":{".class":"SymbolTableNode","cross_ref":"polars.datatypes.group.UNSIGNED_INTEGER_DTYPES","kind":"Gdef"},"__annotations__":{".class":"SymbolTableNode","kind":"Gdef","node":{".class":"Var","flags":["is_ready"],"fullname":"polars.io.database._inference.__annotations__","name":"__annotations__","type":{".class":"Instance","args":["builtins.str",{".class":"AnyType","missing_import_name":null,"source_any":null,"type_of_any":6}],"extra_attrs":null,"type_ref":"builtins.dict"}}},"__doc__":{".class":"SymbolTableNode","kind":"Gdef","node":{".class":"Var","flags":["is_ready"],"fullname":"polars.io.database._inference.__doc__","name":"__doc__","type":"builtins.str"}},"__file__":{".class":"SymbolTableNode","kind":"Gdef","node":{".class":"Var","flags":["is_ready"],"fullname":"polars.io.database._inference.__file__","name":"__file__","type":"builtins.str"}},"__name__":{".class":"SymbolTableNode","kind":"Gdef","node":{".class":"Var","flags":["is_ready"],"fullname":"polars.io.database._inference.__name__","name":"__name__","type":"builtins.str"}},"__package__":{".class":"SymbolTableNode","kind":"Gdef","node":{".class":"Var","flags":["is_ready"],"fullname":"polars.io.database._inference.__package__","name":"__package__","type":"builtins.str"}},"__spec__":{".class":"SymbolTableNode","kind":"Gdef","node":{".class":"Var","flags":["is_ready"],"fullname":"polars.io.database._inference.__spec__","name":"__spec__","type":"_frozen_importlib.ModuleSpec"}},"annotations":{".class":"SymbolTableNode","cross_ref":"__future__.annotations","kind":"Gdef"},"dtype_from_cursor_description":{".class":"SymbolTableNode","kind":"Gdef","node":{".class":"FuncDef","abstract_status":0,"arg_kinds":[0],"arg_names":["description"],"dataclass_transform_spec":null,"deprecated":null,"flags":[],"fullname":"polars.io.database._inference.dtype_from_cursor_description","name":"dtype_from_cursor_description","type":{".class":"CallableType","arg_kinds":[0],"arg_names":["description"],"arg_types":[{".class":"Instance","args":[{".class":"AnyType","missing_import_name":null,"source_any":null,"type_of_any":2}],"extra_attrs":null,"type_ref":"builtins.tuple"}],"bound_args":[],"def_extras":{"first_arg":null},"fallback":"builtins.function","from_concatenate":false,"implicit":false,"imprecise_arg_kinds":false,"is_ellipsis_args":false,"name":"dtype_from_cursor_description","ret_type":{".class":"UnionType","items":[{".class":"TypeAliasType","args":[],"type_ref":"polars._typing.PolarsDataType"},{".class":"NoneType"}],"uses_pep604_syntax":true},"type_guard":null,"type_is":null,"unpack_kwargs":false,"variables":[]}}},"dtype_from_database_typename":{".class":"SymbolTableNode","kind":"Gdef","node":{".class":"FuncDef","abstract_status":0,"arg_kinds":[0,5],"arg_names":["value","raise_unmatched"],"dataclass_transform_spec":null,"deprecated":null,"flags":[],"fullname":"polars.io.database._inference.dtype_from_database_typename","name":"dtype_from_database_typename","type":{".class":"CallableType","arg_kinds":[0,5],"arg_names":["value","raise_unmatched"],"arg_types":["builtins.str","builtins.bool"],"bound_args":[],"def_extras":{"first_arg":null},"fallback":"builtins.function","from_concatenate":false,"implicit":false,"imprecise_arg_kinds":false,"is_ellipsis_args":false,"name":"dtype_from_database_typename","ret_type":{".class":"UnionType","items":[{".class":"TypeAliasType","args":[],"type_ref":"polars._typing.PolarsDataType"},{".class":"NoneType"}],"uses_pep604_syntax":true},"type_guard":null,"type_is":null,"unpack_kwargs":false,"variables":[]}}},"functools":{".class":"SymbolTableNode","cross_ref":"functools","kind":"Gdef"},"integer_dtype_from_nbits":{".class":"SymbolTableNode","kind":"Gdef","node":{".class":"Decorator","func":{".class":"FuncDef","abstract_status":0,"arg_kinds":[0,3,5],"arg_names":["bits","unsigned","default"],"dataclass_transform_spec":null,"deprecated":null,"flags":["is_decorated"],"fullname":"polars.io.database._inference.integer_dtype_from_nbits","name":"integer_dtype_from_nbits","type":{".class":"CallableType","arg_kinds":[0,3,5],"arg_names":["bits","unsigned","default"],"arg_types":["builtins.int","builtins.bool",{".class":"UnionType","items":[{".class":"TypeAliasType","args":[],"type_ref":"polars._typing.PolarsDataType"},{".class":"NoneType"}],"uses_pep604_syntax":true}],"bound_args":[],"def_extras":{"first_arg":null},"fallback":"builtins.function","from_concatenate":false,"implicit":false,"imprecise_arg_kinds":false,"is_ellipsis_args":false,"name":"integer_dtype_from_nbits","ret_type":{".class":"UnionType","items":[{".class":"TypeAliasType","args":[],"type_ref":"polars._typing.PolarsDataType"},{".class":"NoneType"}],"uses_pep604_syntax":true},"type_guard":null,"type_is":null,"unpack_kwargs":false,"variables":[]}},"is_overload":false,"var":{".class":"Var","flags":["is_ready","is_inferred"],"fullname":"polars.io.database._inference.integer_dtype_from_nbits","name":"integer_dtype_from_nbits","type":{".class":"Instance","args":[{".class":"UnionType","items":["polars.datatypes.classes.DataTypeClass","polars.datatypes.classes.DataType",{".class":"NoneType"}],"uses_pep604_syntax":false}],"extra_attrs":null,"type_ref":"functools._lru_cache_wrapper"}}}},"isclass":{".class":"SymbolTableNode","cross_ref":"inspect.isclass","kind":"Gdef"},"parse_py_type_into_dtype":{".class":"SymbolTableNode","cross_ref":"polars.datatypes._parse.parse_py_type_into_dtype","kind":"Gdef"},"re":{".class":"SymbolTableNode","cross_ref":"re","kind":"Gdef"},"suppress":{".class":"SymbolTableNode","cross_ref":"contextlib.suppress","kind":"Gdef"},"timeunit_from_precision":{".class":"SymbolTableNode","kind":"Gdef","node":{".class":"FuncDef","abstract_status":0,"arg_kinds":[0],"arg_names":["precision"],"dataclass_transform_spec":null,"deprecated":null,"flags":[],"fullname":"polars.io.database._inference.timeunit_from_precision","name":"timeunit_from_precision","type":{".class":"CallableType","arg_kinds":[0],"arg_names":["precision"],"arg_types":[{".class":"UnionType","items":["builtins.int","builtins.str",{".class":"NoneType"}],"uses_pep604_syntax":true}],"bound_args":[],"def_extras":{"first_arg":null},"fallback":"builtins.function","from_concatenate":false,"implicit":false,"imprecise_arg_kinds":false,"is_ellipsis_args":false,"name":"timeunit_from_precision","ret_type":{".class":"UnionType","items":["builtins.str",{".class":"NoneType"}],"uses_pep604_syntax":true},"type_guard":null,"type_is":null,"unpack_kwargs":false,"variables":[]}}}},"path":"C:\\Users\\Ephel\\AppData\\Local\\Python\\pythoncore-3.14-64\\Lib\\site-packages\\polars\\io\\database\\_inference.py"}