{"data_mtime":1783440328,"dep_lines":[16,17,18,20,14,15,8,10,11,12,1,1,1,1,1,1,1,1,1,1,1,1,1,1,1,1,1,1,1,1,1,1,1,1,1,23,207,208],"dep_prios":[5,5,5,5,5,5,5,10,5,5,5,20,20,20,20,20,20,20,20,20,20,20,20,20,20,20,20,20,20,30,30,30,30,30,30,25,20,20],"dependencies":["prompt_toolkit.formatted_text.base","prompt_toolkit.formatted_text.utils","prompt_toolkit.styles.pygments","prompt_toolkit.lexers.base","prompt_toolkit.document","prompt_toolkit.filters","__future__","re","abc","typing","builtins","collections","html","warnings","traitlets.utils.warnings","contextlib","functools","os","itertools","traceback","sys","logging","json","copy","pprint","inspect","operator","string","types","_frozen_importlib","_typeshed","enum","prompt_toolkit.filters.base","prompt_toolkit.filters.utils","prompt_toolkit.mouse_events"],"hash":"a8b3f9b28316f284c986842c509ff5468f672579","id":"prompt_toolkit.lexers.pygments","ignore_all":true,"interface_hash":"1a29a5941f5a742f40bfac0de58c842e64aeb123","mtime":1761922142,"options":{"allow_redefinition":false,"allow_untyped_globals":false,"always_false":[],"always_true":[],"bazel":false,"check_untyped_defs":false,"disable_bytearray_promotion":false,"disable_error_code":[],"disable_memoryview_promotion":false,"disabled_error_codes":[],"disallow_any_decorated":false,"disallow_any_explicit":false,"disallow_any_expr":false,"disallow_any_generics":false,"disallow_any_unimported":false,"disallow_incomplete_defs":false,"disallow_subclassing_any":false,"disallow_untyped_calls":false,"disallow_untyped_decorators":false,"disallow_untyped_defs":false,"enable_error_code":[],"enabled_error_codes":[],"extra_checks":false,"follow_imports":"normal","follow_imports_for_stubs":false,"follow_untyped_imports":false,"ignore_errors":false,"ignore_missing_imports":false,"implicit_optional":false,"implicit_reexport":true,"local_partial_types":false,"mypyc":false,"old_type_inference":false,"platform":"win32","plugins":[],"strict_bytes":false,"strict_concatenate":false,"strict_equality":false,"strict_optional":true,"warn_no_return":true,"warn_return_any":false,"warn_unreachable":false,"warn_unused_ignores":false},"path":"C:\\Users\\Ephel\\AppData\\Local\\Python\\pythoncore-3.14-64\\Lib\\site-packages\\prompt_toolkit\\lexers\\pygments.py","plugin_data":null,"size":11922,"suppressed":["pygments.lexer","pygments.lexers","pygments.util"],"version_id":"1.15.0"}