{".class":"MypyFile","_fullname":"src.s7_final.final01b_ddb_compact","future_import_flags":[],"is_partial_stub_package":false,"is_stub":false,"names":{".class":"SymbolTable","Path":{".class":"SymbolTableNode","cross_ref":"pathlib.Path","kind":"Gdef"},"__annotations__":{".class":"SymbolTableNode","kind":"Gdef","node":{".class":"Var","flags":["is_ready"],"fullname":"src.s7_final.final01b_ddb_compact.__annotations__","name":"__annotations__","type":{".class":"Instance","args":["builtins.str",{".class":"AnyType","missing_import_name":null,"source_any":null,"type_of_any":6}],"extra_attrs":null,"type_ref":"builtins.dict"}}},"__doc__":{".class":"SymbolTableNode","kind":"Gdef","node":{".class":"Var","flags":["is_ready"],"fullname":"src.s7_final.final01b_ddb_compact.__doc__","name":"__doc__","type":"builtins.str"}},"__file__":{".class":"SymbolTableNode","kind":"Gdef","node":{".class":"Var","flags":["is_ready"],"fullname":"src.s7_final.final01b_ddb_compact.__file__","name":"__file__","type":"builtins.str"}},"__name__":{".class":"SymbolTableNode","kind":"Gdef","node":{".class":"Var","flags":["is_ready"],"fullname":"src.s7_final.final01b_ddb_compact.__name__","name":"__name__","type":"builtins.str"}},"__package__":{".class":"SymbolTableNode","kind":"Gdef","node":{".class":"Var","flags":["is_ready"],"fullname":"src.s7_final.final01b_ddb_compact.__package__","name":"__package__","type":"builtins.str"}},"__spec__":{".class":"SymbolTableNode","kind":"Gdef","node":{".class":"Var","flags":["is_ready"],"fullname":"src.s7_final.final01b_ddb_compact.__spec__","name":"__spec__","type":"_frozen_importlib.ModuleSpec"}},"copy_db":{".class":"SymbolTableNode","kind":"Gdef","node":{".class":"FuncDef","abstract_status":0,"arg_kinds":[],"arg_names":[],"dataclass_transform_spec":null,"deprecated":null,"flags":[],"fullname":"src.s7_final.final01b_ddb_compact.copy_db","name":"copy_db","type":null}},"duckdb":{".class":"SymbolTableNode","cross_ref":"duckdb","kind":"Gdef"},"duckdb_path":{".class":"SymbolTableNode","kind":"Gdef","node":{".class":"Var","flags":["is_inferred","has_explicit_value"],"fullname":"src.s7_final.final01b_ddb_compact.duckdb_path","name":"duckdb_path","type":"pathlib.Path"}},"main":{".class":"SymbolTableNode","kind":"Gdef","node":{".class":"FuncDef","abstract_status":0,"arg_kinds":[1],"arg_names":["is_skipped"],"dataclass_transform_spec":null,"deprecated":null,"flags":[],"fullname":"src.s7_final.final01b_ddb_compact.main","name":"main","type":{".class":"CallableType","arg_kinds":[1],"arg_names":["is_skipped"],"arg_types":["builtins.bool"],"bound_args":[],"def_extras":{"first_arg":null},"fallback":"builtins.function","from_concatenate":false,"implicit":false,"imprecise_arg_kinds":false,"is_ellipsis_args":false,"name":"main","ret_type":{".class":"AnyType","missing_import_name":null,"source_any":null,"type_of_any":1},"type_guard":null,"type_is":null,"unpack_kwargs":false,"variables":[]}}},"proj_path":{".class":"SymbolTableNode","kind":"Gdef","node":{".class":"Var","flags":["is_inferred","has_explicit_value"],"fullname":"src.s7_final.final01b_ddb_compact.proj_path","name":"proj_path","type":"pathlib.Path"}},"ren_db":{".class":"SymbolTableNode","kind":"Gdef","node":{".class":"FuncDef","abstract_status":0,"arg_kinds":[],"arg_names":[],"dataclass_transform_spec":null,"deprecated":null,"flags":[],"fullname":"src.s7_final.final01b_ddb_compact.ren_db","name":"ren_db","type":null}},"settings":{".class":"SymbolTableNode","cross_ref":"config.settings","kind":"Gdef"},"src_path":{".class":"SymbolTableNode","kind":"Gdef","node":{".class":"Var","flags":["is_inferred","has_explicit_value"],"fullname":"src.s7_final.final01b_ddb_compact.src_path","name":"src_path","type":"pathlib.Path"}},"sys":{".class":"SymbolTableNode","cross_ref":"sys","kind":"Gdef"},"temp_path":{".class":"SymbolTableNode","kind":"Gdef","node":{".class":"Var","flags":["is_inferred","has_explicit_value"],"fullname":"src.s7_final.final01b_ddb_compact.temp_path","name":"temp_path","type":"pathlib.Path"}},"test_db":{".class":"SymbolTableNode","kind":"Gdef","node":{".class":"FuncDef","abstract_status":0,"arg_kinds":[1],"arg_names":["tbl"],"dataclass_transform_spec":null,"deprecated":null,"flags":[],"fullname":"src.s7_final.final01b_ddb_compact.test_db","name":"test_db","type":{".class":"CallableType","arg_kinds":[1],"arg_names":["tbl"],"arg_types":["builtins.str"],"bound_args":[],"def_extras":{"first_arg":null},"fallback":"builtins.function","from_concatenate":false,"implicit":false,"imprecise_arg_kinds":false,"is_ellipsis_args":false,"name":"test_db","ret_type":{".class":"AnyType","missing_import_name":null,"source_any":null,"type_of_any":1},"type_guard":null,"type_is":null,"unpack_kwargs":false,"variables":[]}}},"warnings":{".class":"SymbolTableNode","cross_ref":"warnings","kind":"Gdef"}},"path":"C:\\Users\\Ephel\\.cookiecutters\\cookiecutter-proj\\{{cookiecutter.__project_slug}}\\src\\s7_final\\final01b_ddb_compact.py"}